setup.py
jss/__init__.py
jss/jss.py
jss.egg-info/PKG-INFO
jss.egg-info/SOURCES.txt
jss.egg-info/dependency_links.txt
jss.egg-info/entry_points.txt
jss.egg-info/requires.txt
jss.egg-info/top_level.txt