Metadata-Version: 1.1
Name: jss
Version: 0.1.0
Summary: JSON processing command line tool based on JSONSelect
Home-page: https://github.com/danvk/jss/
Author: Dan Vanderkam
Author-email: danvdk@gmail.com
License: UNKNOWN
Keywords: css,json,jsonselect
Platform: UNKNOWN
Classifier: Development Status :: 4 - Beta
Classifier: Intended Audience :: Developers
Classifier: License :: OSI Approved :: Apache Software License
Classifier: Topic :: Utilities
Classifier: Topic :: Text Processing
